purl_validator/__init__.py
purl_validator/purls.map
purl_validator-0.0.1b1.dist-info/licenses/AUTHORS.rst
purl_validator-0.0.1b1.dist-info/licenses/CHANGELOG.rst
purl_validator-0.0.1b1.dist-info/licenses/CODE_OF_CONDUCT.rst
purl_validator-0.0.1b1.dist-info/licenses/NOTICE
purl_validator-0.0.1b1.dist-info/licenses/README.rst
purl_validator-0.0.1b1.dist-info/licenses/apache-2.0.LICENSE
purl_validator-0.0.1b1.dist-info/METADATA
purl_validator-0.0.1b1.dist-info/WHEEL
purl_validator-0.0.1b1.dist-info/top_level.txt
purl_validator-0.0.1b1.dist-info/RECORD
